upnp_map
