Metadata-Version: 1.0
Name: upnp-map
Version: 0.1.1
Summary: Minimal `upnp-map` tool. Useful to allow TCP conections on port X from the internet to this machine
Home-page: https://github.com/barrabinfc/upnp-map
Author: bbfc
Author-email: rainbrowcorals@gmail.com
License: UNKNOWN
Keywords: upnp,port mapping,firewall-hole,nat-hole,nat-traversal
Platform: UNKNOWN
